xtalx/modbus_adapter/__init__.py
xtalx/modbus_adapter/modbus_adapter.py
xtalx/p_sensor/__init__.py
xtalx/p_sensor/cal_page.py
xtalx/p_sensor/exception.py
xtalx/p_sensor/xhti.py
xtalx/p_sensor/xhtism.py
xtalx/p_sensor/xhtiss.py
xtalx/p_sensor/xhtiss_091.py
xtalx/p_sensor/xhtiss_092.py
xtalx/p_sensor/xmhti.py
xtalx/p_sensor/xti.py
xtalx/spi_adapter/__init__.py
xtalx/spi_adapter/spi_adapter.py
xtalx/tools/config/__init__.py
xtalx/tools/config/config.py
xtalx/tools/csv/__init__.py
xtalx/tools/csv/decoder.py
xtalx/tools/influxdb/__init__.py
xtalx/tools/influxdb/push_queue.py
xtalx/tools/iter/__init__.py
xtalx/tools/iter/prange.py
xtalx/tools/math/__init__.py
xtalx/tools/math/hex_funcs.py
xtalx/tools/math/lorentz.py
xtalx/tools/math/polynomial_fit.py
xtalx/tools/math/xy_series.py
xtalx/tools/modbus/__init__.py
xtalx/tools/modbus/bus.py
xtalx/tools/modbus/modbus_crc.py
xtalx/tools/modbus/serial.py
xtalx/tools/modbus_adapter/__init__.py
xtalx/tools/modbus_adapter/measure_current.py
xtalx/tools/p_sensor/__init__.py
xtalx/tools/p_sensor/csv_resample.py
xtalx/tools/p_sensor/discover.py
xtalx/tools/p_sensor/gl_difference_tool.py
xtalx/tools/p_sensor/gl_track_mode.py
xtalx/tools/p_sensor/lhp_pid_tool.py
xtalx/tools/p_sensor/xhtism_monitor.py
xtalx/tools/p_sensor/xhtism_probe.py
xtalx/tools/p_sensor/xhtism_tool.py
xtalx/tools/p_sensor/xhtiss_monitor.py
xtalx/tools/p_sensor/xhtiss_tool.py
xtalx/tools/p_sensor/xmhti_plot_qspi_data.py
xtalx/tools/p_sensor/xmhti_qspi_decode.py
xtalx/tools/p_sensor/xmhti_tool.py
xtalx/tools/p_sensor/xtalx_freq_tool.py
xtalx/tools/p_sensor/xtalx_test_read.py
xtalx/tools/p_sensor/xtalx_test_read_async.py
xtalx/tools/p_sensor/xtalx_test_yield.py
xtalx/tools/serial/__init__.py
xtalx/tools/spi_adapter/__init__.py
xtalx/tools/spi_adapter/measure_current.py
xtalx/tools/usb/__init__.py
xtalx/tools/z_sensor/__init__.py
xtalx/tools/z_sensor/cli_temp_mode.py
xtalx/tools/z_sensor/cli_track_mode.py
xtalx/tools/z_sensor/discover.py
xtalx/tools/z_sensor/get_info.py
xtalx-1.4.1.dist-info/licenses/LICENSE
xtalx-1.4.1.dist-info/METADATA
xtalx-1.4.1.dist-info/WHEEL
xtalx-1.4.1.dist-info/entry_points.txt
xtalx-1.4.1.dist-info/top_level.txt
xtalx-1.4.1.dist-info/RECORD
