Metadata-Version: 2.4
Name: xtalx
Version: 1.4.1
Summary: Drivers and tools for the XtalX sensor family.
Home-page: https://github.com/phasesensors/xtalx_python
Author: Phase Advanced Sensor Systems Corp.
Author-email: tgreeniaus@phasesensors.com
License: MIT
Keywords: xtalx
Classifier: Operating System :: OS Independent
Classifier: Programming Language :: Python :: 3
Classifier: License :: OSI Approved :: MIT License
Requires-Python: >=3.9
License-File: LICENSE
Requires-Dist: btype>=0.1.7
Requires-Dist: glotlib>=1.0.0
Requires-Dist: influxdb
Requires-Dist: libusb_package>=1.0.26.2
Requires-Dist: numpy
Requires-Dist: pyserial
Requires-Dist: pyusb>=1.2.1
Requires-Dist: scipy
Dynamic: license-file
